syn_reports/__init__.py
syn_reports/_version.py
syn_reports/cli.py
syn_reports/commands/__init__.py
syn_reports/commands/benefactor_permissions_report/__init__.py
syn_reports/commands/benefactor_permissions_report/benefactor_permissions_report.py
syn_reports/commands/benefactor_permissions_report/benefactor_view.py
syn_reports/commands/benefactor_permissions_report/cli.py
syn_reports/commands/entity_permissions_report/__init__.py
syn_reports/commands/entity_permissions_report/cli.py
syn_reports/commands/entity_permissions_report/entity_permissions_report.py
syn_reports/commands/team_access_report/__init__.py
syn_reports/commands/team_access_report/cli.py
syn_reports/commands/team_access_report/team_access_report.py
syn_reports/commands/team_members_report/__init__.py
syn_reports/commands/team_members_report/cli.py
syn_reports/commands/team_members_report/team_members_report.py
syn_reports/commands/user_project_access_report/__init__.py
syn_reports/commands/user_project_access_report/cli.py
syn_reports/commands/user_project_access_report/user_project_access_report.py
syn_reports/commands/user_teams_report/__init__.py
syn_reports/commands/user_teams_report/cli.py
syn_reports/commands/user_teams_report/user_teams_report.py
syn_reports/core/__init__.py
syn_reports/core/utils.py
syn_reports-0.0.19.dist-info/LICENSE
syn_reports-0.0.19.dist-info/METADATA
syn_reports-0.0.19.dist-info/NOTICE
syn_reports-0.0.19.dist-info/WHEEL
syn_reports-0.0.19.dist-info/entry_points.txt
syn_reports-0.0.19.dist-info/top_level.txt
syn_reports-0.0.19.dist-info/RECORD
